{
    "Home": "ホーム",
    "Search": "検索",
    "About us": "私について",
    "Work": "プロジェクト",
    "Contact": "お問い合わせ",
    "Blog": "ブログ",
    "Read more": "続きを読む",
    "Back to Blog": "ブログに戻る",
    "Untranslated Warning": "この記事はあなたの言語に翻訳されていません。オリジナルバージョンを表示しています。",
    "Portfolio Title": "多元宇宙ポートフォリオ",
    "Preferences": "設定",
    "Interface": "インターフェース",
    "Theme": "テーマ",
    "Language": "言語",
    "Network": "ネットワーク",
    "Open Menu": "メニューを開く",
    "Close Menu": "メニューを閉じる",
    "Change Theme": "テーマを変更する",
    "Change Language": "言語を変更する",
    "Thanks for reaching out! I'll get back to you soon.": "ご連絡ありがとうございます！すぐにお返事いたします。",
    "SENDING...": "送信中...",
    "Projects": "プロジェクト",
    "Services": "サービス",
    "Topics": "トピック",
    "Tags": "タグ",
    "Profile": "プロフィール",
    "Read Case Study for": "ケーススタディを読む：",
    "Demo of": "デモ：",
    "Source Code of": "ソースコード：",
    "Hero Background": "ヒーロー背景",
    "Toggle Spline Audio": "Spline の音声を切り替える"
}
